README.rst
setup.py
PolarBird.egg-info/PKG-INFO
PolarBird.egg-info/SOURCES.txt
PolarBird.egg-info/dependency_links.txt
PolarBird.egg-info/entry_points.txt
PolarBird.egg-info/not-zip-safe
PolarBird.egg-info/requires.txt
PolarBird.egg-info/top_level.txt
polarbird/__init__.py
polarbird/colors.py
polarbird/commands.py
polarbird/polarbird.py
polarbird/settings.py
polarbird/streams.py
polarbird/tokens.py
polarbird/tweets.py
polarbird/utils.py
polarbird/windows.py
polarbird/config/config.json