Metadata-Version: 1.1
Name: PolarBird
Version: 0.0.5
Summary: Curses based Twitter app allowing to receive tweets in realtime, compose tweets and more.
Home-page: UNKNOWN
Author: Lukáš Pohlreich
Author-email: pohlreichlukas@gmail.com
License: MIT license
Platform: UNKNOWN
Classifier: Development Status :: 3 - Alpha
Classifier: Environment :: Console :: Curses
Classifier: Programming Language :: Python :: 3.4
Classifier: Programming Language :: Python :: 3.5
Classifier: License :: OSI Approved :: MIT License
Classifier: Natural Language :: English
